pyfairsim/__init__.py
pyfairsim/batch_reconstruction.py
pyfairsim/create_example_settings.py
pyfairsim/parameter_estimation.py
pyfairsim/phase_estimation.py
pyfairsim/reconstruction.py
pyfairsim/tiled_reconstruction.py
pyfairsim/sim_algorithm/Direction.py
pyfairsim/sim_algorithm/OTF_Provider.py
pyfairsim/sim_algorithm/SIM_Parameters.py
pyfairsim/sim_algorithm/SIM_Utils.py
pyfairsim/sim_algorithm/Wiener_Filter.py
pyfairsim/sim_algorithm/__init__.py
pyfairsim/utils/__init__.py
pyfairsim/utils/argparse.py
pyfairsim/utils/load_settings.py
pyfairsim/utils/physics.py
pyfairsim/utils/tif.py
pyfairsim-0.0.3.dist-info/LICENSE
pyfairsim-0.0.3.dist-info/METADATA
pyfairsim-0.0.3.dist-info/WHEEL
pyfairsim-0.0.3.dist-info/top_level.txt
pyfairsim-0.0.3.dist-info/RECORD
