Metadata-Version: 2.1
Name: pyfairsim
Version: 0.0.3
Summary: A package to run sim reconstructions including parameter estimation.
Home-page: 
Author: Jakob Wessendorf
Keywords: sim,reconstruction,parameter estimation
Classifier: Development Status :: 3 - Alpha
Classifier: Programming Language :: Python :: 3
Classifier: Operating System :: Microsoft :: Windows
Requires-Python: >=3
License-File: LICENSE
Requires-Dist: numpy
Requires-Dist: matplotlib
Requires-Dist: scipy
